rf_info/__init__.py
rf_info/cli.py
rf_info/countrymap.py
rf_info/rf_info.py
rf_info/data/__init__.py
rf_info/data/a_allocations.py
rf_info/data/b_allocations.py
rf_info/data/c_allocations.py
rf_info/data/international.py
rf_info/data/rangekeydict.py
rf_info/data/satellites.py
rf_info/data/us.py
rf_info-0.8.0.data/data/share/man/man1/rf-info.1
rf_info-0.8.0.dist-info/AUTHORS.rst
rf_info-0.8.0.dist-info/LICENSE
rf_info-0.8.0.dist-info/METADATA
rf_info-0.8.0.dist-info/WHEEL
rf_info-0.8.0.dist-info/entry_points.txt
rf_info-0.8.0.dist-info/top_level.txt
rf_info-0.8.0.dist-info/RECORD
