Metadata-Version: 2.1
Name: rf-info
Version: 0.8.0
Summary: Python library and command line tool to get Information about a Radio Frequency
Home-page: https://github.com/cosmicc/rf_info
Author: Ian Perry
Author-email: ianperry99@gmail.com
License: MIT license
Keywords: rf_info
Platform: UNKNOWN
Classifier: Development Status :: 2 - Pre-Alpha
Classifier: Intended Audience :: Developers
Classifier: License :: OSI Approved :: MIT License
Classifier: Natural Language :: English
Classifier: Programming Language :: Python :: 3.5
Classifier: Programming Language :: Python :: 3.6
Classifier: Programming Language :: Python :: 3.7
Classifier: Programming Language :: Python :: 3.8
Requires-Python: >=3.5
Requires-Dist: iso3166
Requires-Dist: colorama
